lumberjack/__init__.py
lumberjack/alterations.py
lumberjack/rust/alterations.cpython-35m-x86_64-linux-gnu.so
lumber_jack-0.1.1a0.dist-info/metadata.json
lumber_jack-0.1.1a0.dist-info/RECORD
lumber_jack-0.1.1a0.dist-info/METADATA
lumber_jack-0.1.1a0.dist-info/top_level.txt
lumber_jack-0.1.1a0.dist-info/WHEEL
lumber_jack-0.1.1a0.dist-info/DESCRIPTION.rst
